deepctl_plugin_example/__init__.py
deepctl_plugin_example/command.py
deepctl_plugin_example/models.py
deepctl_plugin_example-0.1.10.dist-info/METADATA
deepctl_plugin_example-0.1.10.dist-info/WHEEL
deepctl_plugin_example-0.1.10.dist-info/entry_points.txt
deepctl_plugin_example-0.1.10.dist-info/top_level.txt
deepctl_plugin_example-0.1.10.dist-info/RECORD
